selenium_datatable/__init__.py
selenium_datatable/container.py
selenium_datatable/datatable.py
selenium_datatable/rowitem.py
selenium_datatable-0.3.3.dist-info/LICENSE
selenium_datatable-0.3.3.dist-info/METADATA
selenium_datatable-0.3.3.dist-info/WHEEL
selenium_datatable-0.3.3.dist-info/top_level.txt
selenium_datatable-0.3.3.dist-info/RECORD
