Metadata-Version: 2.1
Name: selenium-datatable
Version: 0.3.3
Summary: A small library for simplifying a table object in selenium
Home-page: https://github.com/fundakol/selenium_datatable
Author: Lukasz Fundakowski
Author-email: fundakol@yahoo.com
License: UNKNOWN
Keywords: selenium table data-table testing
Platform: UNKNOWN
Classifier: Development Status :: 5 - Production/Stable
Classifier: Programming Language :: Python :: 3
Classifier: Programming Language :: Python :: 3.6
Classifier: Programming Language :: Python :: 3.7
Classifier: Programming Language :: Python :: 3.8
Classifier: Programming Language :: Python :: 3.9
Classifier: License :: OSI Approved :: Apache Software License
Classifier: Operating System :: OS Independent
License-File: LICENSE
Requires-Dist: selenium
